py_agua_iot/__init__.py
py_agua_iot/formula_parser.py
py_agua_iot-0.0.22.dist-info/LICENSE
py_agua_iot-0.0.22.dist-info/METADATA
py_agua_iot-0.0.22.dist-info/WHEEL
py_agua_iot-0.0.22.dist-info/top_level.txt
py_agua_iot-0.0.22.dist-info/RECORD
