Metadata-Version: 2.1
Name: py-agua-iot
Version: 0.0.22
Summary: py-agua-iot provides controlling heating devices connected via the IOT Agua platform of Micronova
Home-page: https://github.com/fredericvl/py-agua-iot
Author: Frederic Van Linthoudt
Author-email: frederic.van.linthoudt@gmail.com
Classifier: Programming Language :: Python :: 3
Classifier: License :: OSI Approved :: Apache Software License
Classifier: Operating System :: OS Independent
License-File: LICENSE
Requires-Dist: PyJWT >=2.1.0
Requires-Dist: requests >=2.25.1
